prismo/Untitled.ipynb
prismo/__init__.py
prismo/control.py
prismo/gui.py
prismo/notebook_demo.ipynb
prismo/prog_example.ipynb
prismo/setup6.ipynb
prismo/test/.zgroup
prismo/test/.zmetadata
prismo/test/main/.zattrs
prismo/test/main/.zgroup
prismo/test/main/bla/.zarray
prismo/test/main/bla/.zattrs
prismo/test/main/bla/0
prismo/test/main/channel/.zarray
prismo/test/main/channel/.zattrs
prismo/test/main/channel/0
prismo/test/main/main/.zarray
prismo/test/main/main/.zattrs
prismo/test/main/main/0.0.0.0.0.0
prismo/test/main/main/0.0.0.1.0.0
prismo/test/main/main/0.0.1.0.0.0
prismo/test/main/main/0.0.1.1.0.0
prismo/test/main/main/0.1.0.0.0.0
prismo/test/main/main/0.1.0.1.0.0
prismo/test/main/main/0.1.1.0.0.0
prismo/test/main/main/0.1.1.1.0.0
prismo/test/main/main/0.2.0.0.0.0
prismo/test/main/main/0.2.0.1.0.0
prismo/test/main/main/0.2.1.0.0.0
prismo/test/main/main/0.2.1.1.0.0
prismo/test/main/main/0.3.0.0.0.0
prismo/test/main/main/0.3.0.1.0.0
prismo/test/main/main/0.3.1.0.0.0
prismo/test/main/main/0.3.1.1.0.0
prismo/test/main/main/0.4.0.0.0.0
prismo/test/main/main/0.4.0.1.0.0
prismo/test/main/main/0.4.1.0.0.0
prismo/test/main/main/0.4.1.1.0.0
prismo/test/main/main/1.0.0.0.0.0
prismo/test/main/main/1.0.0.1.0.0
prismo/test/main/main/1.0.1.0.0.0
prismo/test/main/main/1.0.1.1.0.0
prismo/test/main/main/1.1.0.0.0.0
prismo/test/main/main/1.1.0.1.0.0
prismo/test/main/main/1.1.1.0.0.0
prismo/test/main/main/1.1.1.1.0.0
prismo/test/main/main/1.2.0.0.0.0
prismo/test/main/main/1.2.0.1.0.0
prismo/test/main/main/1.2.1.0.0.0
prismo/test/main/main/1.2.1.1.0.0
prismo/test/main/main/1.3.0.0.0.0
prismo/test/main/main/1.3.0.1.0.0
prismo/test/main/main/1.3.1.0.0.0
prismo/test/main/main/1.3.1.1.0.0
prismo/test/main/main/1.4.0.0.0.0
prismo/test/main/main/1.4.0.1.0.0
prismo/test/main/main/1.4.1.0.0.0
prismo/test/main/main/1.4.1.1.0.0
prismo/test.py
prismo/widgets.py
prismo-0.0.1.dist-info/LICENSE
prismo-0.0.1.dist-info/METADATA
prismo-0.0.1.dist-info/WHEEL
prismo-0.0.1.dist-info/RECORD
