Metadata-Version: 2.1
Name: prismo
Version: 0.0.1
Summary: A microscopy image acquisition toolkit.
Author: Karl Krauth
Author-email: karl.krauth@gmail.com
Requires-Python: >=3.8,<3.13
Classifier: Programming Language :: Python :: 3
Classifier: Programming Language :: Python :: 3.8
Classifier: Programming Language :: Python :: 3.9
Classifier: Programming Language :: Python :: 3.10
Classifier: Programming Language :: Python :: 3.11
Classifier: Programming Language :: Python :: 3.12
